modicons/__init__.py
modicons-0.1.0.dist-info/METADATA
modicons-0.1.0.dist-info/WHEEL
modicons-0.1.0.dist-info/licenses/LICENSE
modicons-0.1.0.dist-info/RECORD
